LICENSE
MANIFEST.in
README.rst
setup.py
flaskstrap/__init__.py
flaskstrap/__main__.py
flaskstrap/commands.py
flaskstrap/config.py
flaskstrap/create_ini.py
flaskstrap/create_nginx_conf.py
flaskstrap/create_project.py
flaskstrap/flaskstrap.py
flaskstrap/settings.py
flaskstrap/setup_server.py
flaskstrap/stuff.py
flaskstrap/utils.py
flaskstrap.egg-info/PKG-INFO
flaskstrap.egg-info/SOURCES.txt
flaskstrap.egg-info/dependency_links.txt
flaskstrap.egg-info/entry_points.txt
flaskstrap.egg-info/not-zip-safe
flaskstrap.egg-info/requires.txt
flaskstrap.egg-info/top_level.txt
flaskstrap/templates/__main__.py
flaskstrap/templates/bootstrap.py
flaskstrap/templates/helloworld.py
flaskstrap/templates/makefile
flaskstrap/templates/nginx_conf
flaskstrap/templates/run_app.sh
flaskstrap/templates/unit-tests.py