Metadata-Version: 1.0
Name: flaskstrap
Version: 0.3.6
Summary: Easily create a flask, nginx, uwsgi and bootstrap project ready for deployment
Home-page: https://github.com/logileifs/flaskstrap
Author: Logi Leifsson
Author-email: logileifs@gmail.com
License: UNKNOWN
Platform: UNKNOWN
